selenium_axe_python/__init__.py
selenium_axe_python/axe-core/axe.min.js
selenium_axe_python/axe.py
selenium_axe_python/py.typed
selenium_axe_python/tests/__init__.py
selenium_axe_python/tests/conftest.py
selenium_axe_python/tests/pytest.ini
selenium_axe_python/tests/test_axe.py
selenium_axe_python/tests/test_page.html
selenium_axe_python-2.2.0.dist-info/LICENSE.txt
selenium_axe_python-2.2.0.dist-info/METADATA
selenium_axe_python-2.2.0.dist-info/WHEEL
selenium_axe_python-2.2.0.dist-info/RECORD
