Metadata-Version: 2.3
Name: selenium-axe-python
Version: 2.2.0
Summary: Python library to integrate axe and selenium for web accessibility testing.
License: Mozilla Public License 2.0 (MPL 2.0)
Author: Marcel Wilson
Requires-Python: >=3.9,<4.0
Classifier: Intended Audience :: Developers
Classifier: License :: Other/Proprietary License
Classifier: Natural Language :: English
Classifier: Operating System :: OS Independent
Classifier: Programming Language :: Python :: 3
Classifier: Programming Language :: Python :: 3.9
Classifier: Programming Language :: Python :: 3.10
Classifier: Programming Language :: Python :: 3.11
Classifier: Programming Language :: Python :: 3.12
Classifier: Programming Language :: Python :: 3.13
Classifier: Programming Language :: Python :: 3 :: Only
Provides-Extra: dev
Provides-Extra: test
Requires-Dist: black ; extra == "dev"
Requires-Dist: isort ; extra == "dev"
Requires-Dist: mypy ; extra == "dev"
Requires-Dist: py (>=1.4.9) ; extra == "dev"
Requires-Dist: pytest ; extra == "dev" or extra == "test"
Requires-Dist: pytest-html ; extra == "dev"
Requires-Dist: pytest-mock ; extra == "dev" or extra == "test"
Requires-Dist: ruff ; extra == "dev"
Requires-Dist: selenium (>=4.7.0)
Requires-Dist: setup-selenium-testing ; extra == "dev" or extra == "test"
Requires-Dist: tox ; extra == "dev"
Requires-Dist: typing-extensions (>=4.0)
Project-URL: Repository, https://github.com/bandophahita/selenium-axe-python
